kedro_cache/__init__.py
kedro_cache/config/__init__.py
kedro_cache/config/models.py
kedro_cache/framework/__init__.py
kedro_cache/framework/cli/__init__.py
kedro_cache/framework/cli/cli.py
kedro_cache/framework/cli/cli_utils.py
kedro_cache/framework/cli/env_utils.py
kedro_cache/framework/hooks/__init__.py
kedro_cache/framework/hooks/cache.py
kedro_cache/framework/hooks/cache_hook.py
kedro_cache/framework/hooks/hash.py
kedro_cache/framework/hooks/utils.py
kedro_cache/template/__init__.py
kedro_cache/template/config/cache.yml
kedro_cache/utils/__init__.py
kedro_cache/utils/testing.py
kedro_cache-0.1.1.dist-info/entry_points.txt
kedro_cache-0.1.1.dist-info/LICENSE
kedro_cache-0.1.1.dist-info/WHEEL
kedro_cache-0.1.1.dist-info/METADATA
kedro_cache-0.1.1.dist-info/RECORD
