Metadata-Version: 2.1
Name: kedro-cache
Version: 0.1.1
Summary: A kedro-plugin that adds caching to kedro pipelines
Home-page: https://github.com/AnH0ang/kedro-cache
License: MIT
Keywords: kedro,caching,kedro-plugin,kedro-cache
Author: An Hoang
Author-email: anhoang31415@gmail.com
Requires-Python: >=3.8,<3.11
Classifier: Development Status :: 4 - Beta
Classifier: Environment :: Plugins
Classifier: Framework :: Kedro
Classifier: Intended Audience :: Developers
Classifier: License :: OSI Approved :: MIT License
Classifier: Operating System :: MacOS
Classifier: Operating System :: Microsoft :: Windows
Classifier: Operating System :: POSIX :: Linux
Classifier: Programming Language :: Python :: 3
Classifier: Programming Language :: Python :: 3.8
Classifier: Programming Language :: Python :: 3.9
Classifier: Programming Language :: Python :: 3.10
Classifier: Programming Language :: Python :: 3.10
Classifier: Programming Language :: Python :: 3.7
Classifier: Programming Language :: Python :: 3.8
Classifier: Programming Language :: Python :: 3.9
Requires-Dist: joblib (>=1.2.0)
Requires-Dist: kedro (>=0.18.0)
Requires-Dist: pydantic (>=1.10.2)
Requires-Dist: sqlitedict (>=2.0.0)
Project-URL: Repository, https://github.com/AnH0ang/kedro-cache
